CYuyanBianchengRuanjianWanquanGonglveCYuyanBianchengWang/README.md
CYuyanBianchengRuanjianWanquanGonglveCYuyanBianchengWang/__init__.py
CYuyanBianchengRuanjianWanquanGonglveCYuyanBianchengWang/__main__.py
CYuyanBianchengRuanjianWanquanGonglveCYuyanBianchengWang/file.epub
CYuyanBianchengRuanjianWanquanGonglveCYuyanBianchengWang/index.html
CYuyanBianchengRuanjianWanquanGonglveCYuyanBianchengWang/css/__init__.py
CYuyanBianchengRuanjianWanquanGonglveCYuyanBianchengWang/css/annotations.css
CYuyanBianchengRuanjianWanquanGonglveCYuyanBianchengWang/css/main.css
CYuyanBianchengRuanjianWanquanGonglveCYuyanBianchengWang/css/normalize.css
CYuyanBianchengRuanjianWanquanGonglveCYuyanBianchengWang/css/popup.css
CYuyanBianchengRuanjianWanquanGonglveCYuyanBianchengWang/font/__init__.py
CYuyanBianchengRuanjianWanquanGonglveCYuyanBianchengWang/font/fontello.eot
CYuyanBianchengRuanjianWanquanGonglveCYuyanBianchengWang/font/fontello.svg
CYuyanBianchengRuanjianWanquanGonglveCYuyanBianchengWang/font/fontello.ttf
CYuyanBianchengRuanjianWanquanGonglveCYuyanBianchengWang/font/fontello.woff
CYuyanBianchengRuanjianWanquanGonglveCYuyanBianchengWang/img/__init__.py
CYuyanBianchengRuanjianWanquanGonglveCYuyanBianchengWang/img/annotator-glyph-sprite.png
CYuyanBianchengRuanjianWanquanGonglveCYuyanBianchengWang/img/annotator-icon-sprite.png
CYuyanBianchengRuanjianWanquanGonglveCYuyanBianchengWang/img/apple-touch-icon.png
CYuyanBianchengRuanjianWanquanGonglveCYuyanBianchengWang/img/cancelfullscreen.png
CYuyanBianchengRuanjianWanquanGonglveCYuyanBianchengWang/img/close.png
CYuyanBianchengRuanjianWanquanGonglveCYuyanBianchengWang/img/fullscreen.png
CYuyanBianchengRuanjianWanquanGonglveCYuyanBianchengWang/img/loader.gif
CYuyanBianchengRuanjianWanquanGonglveCYuyanBianchengWang/img/menu-icon.png
CYuyanBianchengRuanjianWanquanGonglveCYuyanBianchengWang/img/save.png
CYuyanBianchengRuanjianWanquanGonglveCYuyanBianchengWang/img/saved.png
c_yuyan_biancheng_ruanjian_wanquan_gonglve_c_yuyan_biancheng_wang-2024.3.5.0.dist-info/METADATA
c_yuyan_biancheng_ruanjian_wanquan_gonglve_c_yuyan_biancheng_wang-2024.3.5.0.dist-info/WHEEL
c_yuyan_biancheng_ruanjian_wanquan_gonglve_c_yuyan_biancheng_wang-2024.3.5.0.dist-info/entry_points.txt
c_yuyan_biancheng_ruanjian_wanquan_gonglve_c_yuyan_biancheng_wang-2024.3.5.0.dist-info/top_level.txt
c_yuyan_biancheng_ruanjian_wanquan_gonglve_c_yuyan_biancheng_wang-2024.3.5.0.dist-info/RECORD
